retail_plan_table/__init__.py
retail_plan_table/frontend/build/asset-manifest.json
retail_plan_table/frontend/build/favicon.ico
retail_plan_table/frontend/build/index.html
retail_plan_table/frontend/build/logo192.png
retail_plan_table/frontend/build/logo512.png
retail_plan_table/frontend/build/manifest.json
retail_plan_table/frontend/build/robots.txt
retail_plan_table/frontend/build/static/css/main.8a62e2cd.css
retail_plan_table/frontend/build/static/css/main.8a62e2cd.css.map
retail_plan_table/frontend/build/static/js/main.dee76dac.js
retail_plan_table/frontend/build/static/js/main.dee76dac.js.LICENSE.txt
retail_plan_table/frontend/build/static/js/main.dee76dac.js.map
retail_plan_table-5.7.0.dist-info/METADATA
retail_plan_table-5.7.0.dist-info/WHEEL
retail_plan_table-5.7.0.dist-info/top_level.txt
retail_plan_table-5.7.0.dist-info/RECORD
