Metadata-Version: 2.1
Name: retail-plan-table
Version: 5.7.0
Home-page: 
Author: 
Author-email: 
Requires-Python: >=3.6
Requires-Dist: streamlit >=0.66
